pydecodr/__init__.py
pydecodr/api.py
pydecodr/cli.py
pydecodr/ciphers/__init.py
pydecodr/ciphers/classical/__init__.py
pydecodr/ciphers/classical/affine.py
pydecodr/ciphers/classical/atbash.py
pydecodr/ciphers/classical/bacon.py
pydecodr/ciphers/classical/caesar.py
pydecodr/ciphers/classical/gronsfeld.py
pydecodr/ciphers/classical/hill.py
pydecodr/ciphers/classical/homophonic.py
pydecodr/ciphers/classical/rot13.py
pydecodr/ciphers/classical/rot47.py
pydecodr/ciphers/classical/substitution.py
pydecodr/ciphers/fractionation/__init__.py
pydecodr/ciphers/fractionation/adfgvx.py
pydecodr/ciphers/fractionation/adfgx.py
pydecodr/ciphers/fractionation/bazeries.py
pydecodr/ciphers/fractionation/bifid.py
pydecodr/ciphers/fractionation/four_square.py
pydecodr/ciphers/fractionation/nihilist.py
pydecodr/ciphers/fractionation/polybius.py
pydecodr/ciphers/fractionation/trifid.py
pydecodr/ciphers/modern/__init__.py
pydecodr/ciphers/modern/aes.py
pydecodr/ciphers/modern/hashes.py
pydecodr/ciphers/modern/rsa.py
pydecodr/ciphers/polyalphabetic/__init__.py
pydecodr/ciphers/polyalphabetic/autokey_vigenere.py
pydecodr/ciphers/polyalphabetic/beaufort.py
pydecodr/ciphers/polyalphabetic/playfair.py
pydecodr/ciphers/polyalphabetic/porta.py
pydecodr/ciphers/polyalphabetic/running_key.py
pydecodr/ciphers/polyalphabetic/vigenere.py
pydecodr/ciphers/rotor/__init__.py
pydecodr/ciphers/rotor/enigma.py
pydecodr/ciphers/stream/__init__.py
pydecodr/ciphers/stream/rc4.py
pydecodr/ciphers/stream/repeating_xor.py
pydecodr/ciphers/stream/xor.py
pydecodr/ciphers/transposition/__init__.py
pydecodr/ciphers/transposition/columnar.py
pydecodr/ciphers/transposition/double_transposition.py
pydecodr/ciphers/transposition/myszkowski.py
pydecodr/ciphers/transposition/railfence.py
pydecodr/ciphers/transposition/route_cipher.py
pydecodr/detectors/__init__.py
pydecodr/detectors/autodetect.py
pydecodr/detectors/file_magic.py
pydecodr/encodings/__init__.py
pydecodr/encodings/base32_mod.py
pydecodr-0.1.4.dist-info/licenses/LICENSE
pydecodr-0.1.4.dist-info/METADATA
pydecodr-0.1.4.dist-info/WHEEL
pydecodr-0.1.4.dist-info/top_level.txt
pydecodr-0.1.4.dist-info/RECORD
