Metadata-Version: 2.4
Name: pydecodr
Version: 0.1.4
Summary: A modular CTF/crypto library toolkit for encodings, classic ciphers, and autodetection. CLI included :3.
Author-email: Adelin Sofian <adelin@hackclub.app>
License: MIT
Project-URL: Homepage, https://pypi.org/project/pydecodr/
Project-URL: Repository, https://github.com/xndadelin/pydecodr
Project-URL: Issues, https://github.com/xndadelin/pydecodr/issues
Keywords: cryptography,ctf,encoding,cipher,python3
Requires-Python: >=3.8
License-File: LICENSE
Requires-Dist: pycryptodome>=3.20.0
Requires-Dist: numpy>=1.26.0
Requires-Dist: rich>=13.7.0
Requires-Dist: typer>=0.12.3
Provides-Extra: dev
Requires-Dist: pytest>=8.0.0; extra == "dev"
Dynamic: license-file
